<?xml version="1.0"?>

<!-- ***** BEGIN LICENSE BLOCK *****
 Version: MPL 1.1/GPL 2.0/LGPL 2.1
 
 The contents of this file are subject to the Mozilla Public License
 Version 1.1 (the "License"); you may not use this file except in
 compliance with the License. You may obtain a copy of the License at
 http://www.mozilla.org/MPL/
 
 Software distributed under the License is distributed on an "AS IS"
 basis, WITHOUT WARRANTY OF ANY KIND, either express or implied. See the
 License for the specific language governing rights and limitations
 under the License.
 
 The Original Code is Komodo code.
 
 The Initial Developer of the Original Code is ActiveState Software Inc.
 Portions created by ActiveState Software Inc are Copyright (C) 2000-2007
 ActiveState Software Inc. All Rights Reserved.
 
 Contributor(s):
   ActiveState Software Inc
 
 Alternatively, the contents of this file may be used under the terms of
 either the GNU General Public License Version 2 or later (the "GPL"), or
 the GNU Lesser General Public License Version 2.1 or later (the "LGPL"),
 in which case the provisions of the GPL or the LGPL are applicable instead
 of those above. If you wish to allow use of your version of this file only
 under the terms of either the GPL or the LGPL, and not to allow others to
 use your version of this file under the terms of the MPL, indicate your
 decision by deleting the provisions above and replace them with the notice
 and other provisions required by the GPL or the LGPL. If you do not delete
 the provisions above, a recipient may use your version of this file under
 the terms of any one of the MPL, the GPL or the LGPL.
 
 ***** END LICENSE BLOCK ***** -->

<!DOCTYPE bindings PUBLIC "-//MOZILLA//DTD XBL V1.0//EN" "http://www.mozilla.org/xbl" [
  <!ENTITY % bindingsDTD SYSTEM "chrome://komodo/locale/bindings.dtd">
  %bindingsDTD;
]>

<bindings xmlns="http://www.mozilla.org/xbl"
          xmlns:xbl="http://www.mozilla.org/xbl"
          xmlns:html="http://www.w3.org/1999/xhtml"
          xmlns:xul="http://www.mozilla.org/keymaster/gatekeeper/there.is.only.xul">

    <!-- Toolbar that will make any overflowed items visible through a -->
    <binding id="toolbar-overflow"
             extends="chrome://global/content/bindings/general.xml#basecontrol">

        <content>
            <children />
        </content>

        <implementation implements="nsIDOMEventListener">
            <constructor>
                <![CDATA[
                window.addEventListener("resize", this, false);
                ]]>
            </constructor>
            <destructor>
                <![CDATA[
                if (this._updateTimerId) {
                    window.clearTimeout(this._updateTimerId);
                }
                window.removeEventListener("resize", this, false);
                ]]>
            </destructor>

            <!-- Element to enable/disable when overflowed/underflowed. -->
            <field name="toolbar_overflow">null</field>

            <field name="_updateTimerId">0</field>

            <method name="_updateChildVisibility_callback">
              <parameter name="event" />
              <body>
              <![CDATA[
                let scrollRect = this.getBoundingClientRect();
                let childOverflowed = false;
                for (let i=0; i < this.childNodes.length; i++) {
                    let child = this.childNodes[i];
                    // Once a child overflows, all the next ones will.
                    if (!childOverflowed) {
                      let childRect = child.getBoundingClientRect();
                      childOverflowed = childRect.right > scrollRect.right;
                    }
                    child.style.visibility = childOverflowed ? "hidden" : "visible";
                }
                if (this.toolbar_overflow) {
                    if (childOverflowed) {
                        this.toolbar_overflow.removeAttribute("disabled");
                    } else {
                        this.toolbar_overflow.setAttribute("disabled", "true");
                    }
                }
              ]]>
              </body>
            </method>

            <method name="_updateChildVisibility">
              <parameter name="event" />
              <body>
              <![CDATA[
                // Use a timeout to avoid quickly repeated calls.
                if (this._updateTimerId) {
                    window.clearTimeout(this._updateTimerId);
                }
                this._updateTimerId = window.setTimeout(
                        function(self) {
                            self._updateChildVisibility_callback();
                        },
                        50, this);
              ]]>
              </body>
            </method>

            <method name="handleEvent">
              <parameter name="event" />
              <body>
              <![CDATA[
                switch (event.type) {
                    case "resize":
                        this._updateChildVisibility(event);
                        break;
                }
              ]]>
              </body>
            </method>
        </implementation>

        <handlers>
            <handler event="underflow" phase="capturing">
            <![CDATA[
                this._updateChildVisibility(event);
            ]]>
            </handler>
            <handler event="overflow" phase="capturing">
            <![CDATA[
                this._updateChildVisibility(event);
            ]]>
            </handler>
        </handlers>

    </binding>

</bindings>

